README
setup.cfg
setup.py
fraciso/__init__.py
fraciso/isomorphism.py
fraciso/linprog.py
fraciso/matrices.py
fraciso/partitions.py
fraciso.egg-info/PKG-INFO
fraciso.egg-info/SOURCES.txt
fraciso.egg-info/dependency_links.txt
fraciso.egg-info/not-zip-safe
fraciso.egg-info/requires.txt
fraciso.egg-info/top_level.txt