Metadata-Version: 1.1
Name: fraciso
Version: 0.0.7
Summary: Algorithms for fractional graph isomorphism
Home-page: https://github.com/jfinkels/fraciso
Author: Jeffrey Finkelstein
Author-email: jeffrey.finkelstein@gmail.com
License: GNU GPLv3+
Download-URL: https://github.com/jfinkels/fraciso
Platform: any
